{
  "pdf_word": {
    "title": "Document Title",
    "author": "AI Writer",
    "language": "English",
    "sections": [
      {
        "heading": "Introduction",
        "paragraph": "Summarized content for this section. This provides an overview of the topic. The reader will gain a foundational understanding.",
        "bullets": [
          "Key Point 1",
          "Key Point 2",
          "Key Point 3"
        ],
        "image_keyword": "illustration keyword"
      },
      {
        "heading": "Details",
        "paragraph": "Expanded content with examples. Multiple perspectives are considered. Practical applications are explored.",
        "bullets": [
          "Detail 1",
          "Detail 2",
          "Detail 3"
        ],
        "image_keyword": "optional illustration keyword"
      }
    ]
  }
}
